{
  "project_info": {
    "project_number": "51424700179",
    "project_id": "my-food-app-s143",
    "storage_bucket": "my-food-app-s143.appspot.com"
  },
  "client": [
    {
      "client_info": {
        "mobilesdk_app_id": "1:51424700179:android:bcb4380edca466ea885ce6",
        "android_client_info": {
          "package_name": "com.example.my_firebase"
        }
      },
      "oauth_client": [
        {
          "client_id": "51424700179-81ftnqn2tpihl68cbjs8cuc7ngp1g8lp.apps.googleusercontent.com",
          "client_type": 3
        }
      ],
      "api_key": [
        {
          "current_key": "AIzaSyD5Y3re_HgxdM0qqdIWhRi7SVQqAQibtmA"
        }
      ],
      "services": {
        "appinvite_service": {
          "other_platform_oauth_client": [
            {
              "client_id": "51424700179-81ftnqn2tpihl68cbjs8cuc7ngp1g8lp.apps.googleusercontent.com",
              "client_type": 3
            }
          ]
        }
      }
    },
    {
      "client_info": {
        "mobilesdk_app_id": "1:51424700179:android:d25835e4f0461101885ce6",
        "android_client_info": {
          "package_name": "com.example.my_food_application"
        }
      },
      "oauth_client": [
        {
          "client_id": "51424700179-81ftnqn2tpihl68cbjs8cuc7ngp1g8lp.apps.googleusercontent.com",
          "client_type": 3
        }
      ],
      "api_key": [
        {
          "current_key": "AIzaSyD5Y3re_HgxdM0qqdIWhRi7SVQqAQibtmA"
        }
      ],
      "services": {
        "appinvite_service": {
          "other_platform_oauth_client": [
            {
              "client_id": "51424700179-81ftnqn2tpihl68cbjs8cuc7ngp1g8lp.apps.googleusercontent.com",
              "client_type": 3
            }
          ]
        }
      }
    }
  ],
  "configuration_version": "1"
}